pyusel/__init__.py
pyusel-0.0.0.dist-info/LICENSE
pyusel-0.0.0.dist-info/METADATA
pyusel-0.0.0.dist-info/WHEEL
pyusel-0.0.0.dist-info/top_level.txt
pyusel-0.0.0.dist-info/RECORD
