Metadata-Version: 2.1
Name: pyusel
Version: 0.0.0
Summary: Ultrasound Elasticity Imaging Toolkit
Author: Wren Wightman
Author-email: Wren Wightman <wren.wightman@duke.edu>
Project-URL: Homepage, https://github.com/wewightman/pyusel
Classifier: Programming Language :: Python :: 3
Classifier: License :: OSI Approved :: MIT License
Classifier: Operating System :: OS Independent
Requires-Python: >=3.7
License-File: LICENSE
Requires-Dist: pyusel-dispest
